gym_industrial/__init__.py
gym_industrial/envs/__init__.py
gym_industrial/envs/effective_action.py
gym_industrial/envs/ids.py
gym_industrial/envs/industrial_benchmark.py
gym_industrial/envs/goldstone/__init__.py
gym_industrial/envs/goldstone/dynamics.py
gym_industrial/envs/goldstone/environment.py
tests/__init__.py
tests/test_basic.py
tests/test_industrial_benchmark.py
gym_industrial-0.0.1.dist-info/LICENCE.txt
gym_industrial-0.0.1.dist-info/METADATA
gym_industrial-0.0.1.dist-info/WHEEL
gym_industrial-0.0.1.dist-info/top_level.txt
gym_industrial-0.0.1.dist-info/RECORD
