Metadata-Version: 2.1
Name: gym-industrial
Version: 0.0.1
Summary: Industrial Benchmark for OpenAI Gym
Home-page: https://github.com/angelolovatto/gym-industrial
Author: Ângelo G. Lovatto
Author-email: angelolovatto@gmail.com
License: UNKNOWN
Platform: UNKNOWN
Classifier: Programming Language :: Python :: 3
Classifier: License :: OSI Approved :: Apache Software License
Classifier: Operating System :: OS Independent
Requires-Python: >=3.7
Requires-Dist: gym
